fillbert_client/__init__.py
fillbert_client/client.py
fillbert_client/models.py
fillbert_client/py.typed
fillbert_client/webhook.py
fillbert_client-0.1.0.dist-info/METADATA
fillbert_client-0.1.0.dist-info/WHEEL
fillbert_client-0.1.0.dist-info/RECORD
