Metadata-Version: 2.4
Name: fillbert-client
Version: 0.1.0
Summary: Python client for Fillbert document processing service
Project-URL: Homepage, https://github.com/jvogel/ocr-api
Project-URL: Repository, https://github.com/jvogel/ocr-api
Project-URL: Issues, https://github.com/jvogel/ocr-api/issues
Author: Fillbert Team
License: MIT
Classifier: Development Status :: 3 - Alpha
Classifier: Intended Audience :: Developers
Classifier: License :: OSI Approved :: MIT License
Classifier: Programming Language :: Python :: 3
Classifier: Programming Language :: Python :: 3.10
Classifier: Programming Language :: Python :: 3.11
Classifier: Programming Language :: Python :: 3.12
Classifier: Programming Language :: Python :: 3.13
Requires-Python: >=3.10
Requires-Dist: httpx
Requires-Dist: pydantic
Requires-Dist: typing-extensions
Provides-Extra: dev
Requires-Dist: fastapi; extra == 'dev'
Requires-Dist: pytest; extra == 'dev'
Requires-Dist: pytest-asyncio; extra == 'dev'
Requires-Dist: pytest-mock; extra == 'dev'
Requires-Dist: respx; extra == 'dev'
Provides-Extra: fastapi
Requires-Dist: fastapi; extra == 'fastapi'
